bitflag/BitFlag.py
bitflag/TestBitFlag.py
bitflag/__init__.py
bitflag-2.0.0.dist-info/METADATA
bitflag-2.0.0.dist-info/RECORD
bitflag-2.0.0.dist-info/WHEEL
bitflag-2.0.0.dist-info/top_level.txt
